weather.py
amapote_moni_mcp_server-0.1.0.dist-info/METADATA
amapote_moni_mcp_server-0.1.0.dist-info/WHEEL
amapote_moni_mcp_server-0.1.0.dist-info/top_level.txt
amapote_moni_mcp_server-0.1.0.dist-info/RECORD
