Metadata-Version: 2.4
Name: amapote-moni-mcp-server
Version: 0.1.0
Summary: 使用API查询中国境内天气。
Requires-Python: >=3.13
Requires-Dist: datetime>=5.5
Requires-Dist: httpx>=0.28.1
Requires-Dist: mcp[cli]>=1.6.0
Requires-Dist: requests>=2.32.3
Requires-Dist: requests>=2.32.3
